setup.py
upfluence/__init__.py
upfluence/error_logger/__init__.py
upfluence/error_logger/noop.py
upfluence/error_logger/opbeat_wrapper.py
upfluence/log/__init__.py
upfluence/thrift/__init__.py
upfluence/thrift/base_handler.py
upfluence/thrift/decorator/__init__.py
upfluence/thrift/decorator/catcher.py
upfluence/thrift/decorator/logger.py
upfluence/tracing/statsd.py
upfluence_utils.egg-info/PKG-INFO
upfluence_utils.egg-info/SOURCES.txt
upfluence_utils.egg-info/dependency_links.txt
upfluence_utils.egg-info/requires.txt
upfluence_utils.egg-info/top_level.txt