Metadata-Version: 1.0
Name: upfluence-utils
Version: 0.1.7
Summary: set of utils used at Upfluence
Home-page: https://github.com/upfluence/pyutils
Author: Alexis Montagne
Author-email: alexis.montagne@upfluence.co
License: UNKNOWN
Platform: UNKNOWN
